setup.py
LocalGrowl.egg-info/PKG-INFO
LocalGrowl.egg-info/SOURCES.txt
LocalGrowl.egg-info/dependency_links.txt
LocalGrowl.egg-info/requires.txt
LocalGrowl.egg-info/top_level.txt
localgrowl/__init__.py
localgrowl/growl.py
