Metadata-Version: 1.0
Name: LocalGrowl
Version: 0.2
Summary: Python implemenation of Growl notifications.
Home-page: http://pypi.python.org/pypi/LocalGrowl
Author: Travis Jeffery
Author-email: t.jeffery@utoronto.ca
License: GPL
Keywords: growl python localhost local
Platform: UNKNOWN
